prompts/__init__.py
simple_gui_prompts-1.1.0.dist-info/LICENSE
simple_gui_prompts-1.1.0.dist-info/METADATA
simple_gui_prompts-1.1.0.dist-info/WHEEL
simple_gui_prompts-1.1.0.dist-info/top_level.txt
simple_gui_prompts-1.1.0.dist-info/RECORD
