Metadata-Version: 2.1
Name: simple-gui-prompts
Version: 1.1.0
Summary: Easily generate GUI prompts without the hassle of making a whole GUI
Home-page: https://gitlab.com/0100001001000010/simple-gui-prompts
Author: Bruce Blore
Author-email: bruceblore@protonmail.com
License: UNKNOWN
Platform: UNKNOWN
Classifier: Programming Language :: Python :: 3
Classifier: License :: OSI Approved :: MIT License
Classifier: Operating System :: OS Independent
Requires-Python: >=3.6
Requires-Dist: pysimplegui
